<Billet Fichier="a-propos" TitreCourt="A propos">
  <Meta>
    <DateCreation>2021-04-15</DateCreation>
    <Auteur>Chitoaxol</Auteur>    
  </Meta>
  <Titre>A propos
  </Titre>
  <Chapo>Naissance du site sceptique.fr
  </Chapo>  
  <Corps>
Ce blog est né de mon désir de quitter le navire Mediapart après que l'un de mes commentaires fut censuré. 

À l'origine il s'agit de quelques billets écrits au cours de l'année 2020 comme exutoire et comme hygiène mentale pour ne pas rester totalement muet devant la gestion de la crise sanitaire totalement démente qui nous a été imposée.
  </Corps>
</Billet>

